article_crawler/__init__.py
article_crawler/__main__.py
article_crawler/article_crawler.py
article_crawler/csdn/__init__.py
article_crawler/csdn/csdn_crawler.py
article_crawler/jianshu/__init__.py
article_crawler/jianshu/jianshu_crawler.py
article_crawler/juejin/__init__.py
article_crawler/juejin/juejin_crawler.py
article_crawler/zhihu/__init__.py
article_crawler/zhihu/zhihu_crawler.py
article_crawler-0.0.4.dist-info/LICENSE
article_crawler-0.0.4.dist-info/METADATA
article_crawler-0.0.4.dist-info/WHEEL
article_crawler-0.0.4.dist-info/top_level.txt
article_crawler-0.0.4.dist-info/RECORD
