Metadata-Version: 2.1
Name: article-crawler
Version: 0.0.4
Summary: A package for crawling markdown formatted articles from certain webpage and storing them locally.
Author: ltyzzz (Tycho)
Author-email: ltyzzz2000@gmail.com
Keywords: python,markdown,pdf,article,crawler
Classifier: Development Status :: 1 - Planning
Classifier: Intended Audience :: Developers
Classifier: Programming Language :: Python :: 3
Classifier: Operating System :: Unix
Classifier: Operating System :: MacOS :: MacOS X
Classifier: Operating System :: Microsoft :: Windows
License-File: LICENSE
Requires-Dist: bs4
Requires-Dist: html2text
Requires-Dist: parsel
Requires-Dist: requests
